MANIFEST.in
README.rst
setup.py
presstatic/__init__.py
presstatic/__main__.py
presstatic/builder.py
presstatic/help.py
presstatic/http.py
presstatic/utils.py
presstatic/watcher.py
presstatic.egg-info/PKG-INFO
presstatic.egg-info/SOURCES.txt
presstatic.egg-info/dependency_links.txt
presstatic.egg-info/entry_points.txt
presstatic.egg-info/requires.txt
presstatic.egg-info/top_level.txt
presstatic/storage/__init__.py
presstatic/storage/s3.py