Metadata-Version: 1.1
Name: presstatic
Version: 0.1.0
Summary: Deploy static websites to Amazon S3 easily.
Home-page: https://github.com/regadas/presstatic
Author: Filipe Regadas
Author-email: filipe@regadas.org
License: BSD
Platform: UNKNOWN
Classifier: Environment :: Console
Classifier: Intended Audience :: Developers
Classifier: Natural Language :: English
Classifier: Programming Language :: Python
Classifier: Programming Language :: Python :: 2
Classifier: Programming Language :: Python :: 2.6
Classifier: Programming Language :: Python :: 2.7
Classifier: Programming Language :: Python :: 3
Classifier: Programming Language :: Python :: 3.1
Classifier: Programming Language :: Python :: 3.2
Classifier: License :: OSI Approved :: BSD License
Classifier: Topic :: Internet
Classifier: Topic :: Terminals
Classifier: Topic :: Utilities
